Metadata-Version: 1.1
Name: binge
Version: 0.1.1
Summary: Lazy multiprocess your callables in three extra characters
Home-page: https://github.com/ceyzeriat/binge/
Author: Guillaume Schworer
Author-email: guillaume.schworer@gmail.com
License: GNU General Public License v3 or later (GPLv3+)
Download-URL: https://github.com/ceyzeriat/binge/tree/master/dist
Keywords: multi,processing,multiprocessing,lazy,wrapper,function,threading,multithreading,multi-processing,multi-threading
Platform: UNKNOWN
Classifier: Development Status :: 4 - Beta
Classifier: Environment :: Console
Classifier: Intended Audience :: Developers
Classifier: Intended Audience :: Education
Classifier: Intended Audience :: Science/Research
Classifier: License :: OSI Approved :: GNU General Public License v3 or later (GPLv3+)
Classifier: Operating System :: OS Independent
Classifier: Programming Language :: Python
